README.txt
setup.cfg
setup.py
collective/__init__.py
collective.testing.egg-info/PKG-INFO
collective.testing.egg-info/SOURCES.txt
collective.testing.egg-info/dependency_links.txt
collective.testing.egg-info/entry_points.txt
collective.testing.egg-info/namespace_packages.txt
collective.testing.egg-info/not-zip-safe
collective.testing.egg-info/top_level.txt
collective/testing/__init__.py
collective/testing/browser.zcml
collective/testing/debug.py
collective/testing/hello-world.pt
collective/testing/interfaces.py
collective/testing/layer.py
collective/testing/printevent.zcml
collective/testing/profile.py
collective/testing/subscribers.py
collective/testing/tests.py
collective/testing/traversal.zcml
collective/testing/utils.py
docs/HISTORY.txt
docs/INSTALL.txt
docs/LICENSE.GPL
docs/LICENSE.txt
