Metadata-Version: 1.0
Name: collective.testing
Version: 0.3
Summary: general package for testing and debugging aids for CMF, Plone, Zope2 and Zope3
Home-page: https://svn.plone.org/svn/collective/collective.testing/trunk#egg=collective.testing
Author: whit
Author-email: whit@openplans.org
License: MIT
Keywords: 'testing debug pdb profile zope.testing'
Platform: UNKNOWN
